sindre/__init__.py
sindre/ai/__init__.py
sindre/ai/embedder.py
sindre/ai/init_utils.py
sindre/ai/layers.py
sindre/ai/losses.py
sindre/ai/utils.py
sindre/ai/attention_utils/__init__.py
sindre/ai/attention_utils/cross_attention.py
sindre/ai/attention_utils/multihead_attention.py
sindre/ai/attention_utils/self_attention.py
sindre/ai/attention_utils/models/__init__.py
sindre/ai/attention_utils/models/decoder.py
sindre/ai/attention_utils/models/encoder.py
sindre/ai/attention_utils/models/transformer.py
sindre/ai/demo/DDP_by_label.py
sindre/ai/demo/dental_mv_pcd.py
sindre/ai/demo/multi_view_by_mesh.py
sindre/ai/demo/sindre_generate.py
sindre/ai/demo/sindre_simple_generate.py
sindre/ai/demo/vedo_torch_pose.py
sindre/ai/demo/vedo_torch_seg.py
sindre/ai/dinov2_utils/__init__.py
sindre/ai/dinov2_utils/depth_estimation.py
sindre/ai/dinov2_utils/dinov2_text.py
sindre/ai/dinov2_utils/segmentation.py
sindre/ai/dinov2_utils/similarity_query.py
sindre/ai/dinov2_utils/text.py
sindre/ai/hunyuan3D/Hunyuan3DDiT.py
sindre/ai/hunyuan3D/__init__.py
sindre/ai/implicit_utils/ShapeAttention.py
sindre/ai/implicit_utils/ShapeVAE.py
sindre/ai/implicit_utils/__init__.py
sindre/ai/implicit_utils/conv_occ.py
sindre/ai/implicit_utils/point2voxel.py
sindre/ai/implicit_utils/utils.py
sindre/ai/minkowski_utils/__init__.py
sindre/ai/minkowski_utils/utils.py
sindre/ai/nlp_utils/__init__.py
sindre/ai/nlp_utils/clip_tokenizer.py
sindre/ai/peft_utils/__init__.py
sindre/ai/peft_utils/utils.py
sindre/ai/pointcloud_utils/__init__.py
sindre/ai/pointcloud_utils/augment.py
sindre/ai/pointcloud_utils/dental_utils.py
sindre/ai/pointcloud_utils/dgcnn.py
sindre/ai/pointcloud_utils/layers.py
sindre/ai/pointcloud_utils/point_transformerV3.py
sindre/ai/pointcloud_utils/pointnet2.py
sindre/ai/pointcloud_utils/utils.py
sindre/ai/resnet_utils/__init__.py
sindre/ai/resnet_utils/block.py
sindre/ai/unet_utils/__init__.py
sindre/ai/unet_utils/unet.py
sindre/ai/yolov8_utils/__init__.py
sindre/ai/yolov8_utils/infer.py
sindre-2026.1.20.dist-info/licenses/LICENSE
sindre-2026.1.20.dist-info/METADATA
sindre-2026.1.20.dist-info/WHEEL
sindre-2026.1.20.dist-info/entry_points.txt
sindre-2026.1.20.dist-info/top_level.txt
sindre-2026.1.20.dist-info/RECORD
