Metadata-Version: 2.4
Name: sindre
Version: 2026.1.20
Summary: 自用脚本库
Home-page: https://github.com/SindreYang/Sindre
Author: SindreYang
License: LGPL-3.0-or-later
Requires-Python: >=3.8
License-File: LICENSE
Requires-Dist: lmdb>=1.6.2
Requires-Dist: msgpack>=1.1.0
Requires-Dist: vedo>=2025.5.3
Requires-Dist: numpy<2.0.0
Requires-Dist: loguru
Requires-Dist: tqdm
Requires-Dist: scipy
Requires-Dist: numba
Provides-Extra: full
Requires-Dist: Cython; extra == "full"
Requires-Dist: nvitop; extra == "full"
Requires-Dist: scikit-learn; extra == "full"
Requires-Dist: pyqt5; extra == "full"
Requires-Dist: qdarkstyle; extra == "full"
Requires-Dist: fastapi; extra == "full"
Requires-Dist: opencv-contrib-python; extra == "full"
Requires-Dist: opencv-python; extra == "full"
Requires-Dist: scikit-image; extra == "full"
Requires-Dist: imgaug; extra == "full"
Requires-Dist: matplotlib; extra == "full"
Requires-Dist: Pillow; extra == "full"
Requires-Dist: pymeshlab; extra == "full"
Requires-Dist: meshlib==3.0.6.229; extra == "full"
Requires-Dist: libigl>=2.6.1; extra == "full"
Requires-Dist: trimesh; extra == "full"
Requires-Dist: open3d; extra == "full"
Requires-Dist: pymeshlab; extra == "full"
Provides-Extra: 2d
Requires-Dist: opencv-contrib-python; extra == "2d"
Requires-Dist: opencv-python; extra == "2d"
Requires-Dist: scikit-image; extra == "2d"
Requires-Dist: imgaug; extra == "2d"
Requires-Dist: matplotlib; extra == "2d"
Requires-Dist: Pillow; extra == "2d"
Provides-Extra: 3d
Requires-Dist: pymeshlab; extra == "3d"
Requires-Dist: meshlib==3.0.6.229; extra == "3d"
Requires-Dist: libigl>=2.6.1; extra == "3d"
Requires-Dist: trimesh; extra == "3d"
Requires-Dist: open3d; extra == "3d"
Requires-Dist: pymeshlab; extra == "3d"
Dynamic: author
Dynamic: description
Dynamic: description-content-type
Dynamic: home-page
Dynamic: license
Dynamic: license-file
Dynamic: provides-extra
Dynamic: requires-dist
Dynamic: requires-python
Dynamic: summary
